spacy_stanfordnlp/__init__.py
spacy_stanfordnlp/about.py
spacy_stanfordnlp/language.py
spacy_stanfordnlp-0.1.3.dist-info/LICENSE
spacy_stanfordnlp-0.1.3.dist-info/METADATA
spacy_stanfordnlp-0.1.3.dist-info/WHEEL
spacy_stanfordnlp-0.1.3.dist-info/entry_points.txt
spacy_stanfordnlp-0.1.3.dist-info/top_level.txt
spacy_stanfordnlp-0.1.3.dist-info/RECORD
