Metadata-Version: 2.1
Name: spacy-stanfordnlp
Version: 0.1.3
Summary: Use the latest StanfordNLP research models directly in spaCy
Home-page: https://explosion.ai
Author: Ines Montani
Author-email: ines@explosion.ai
License: MIT
Platform: UNKNOWN
Classifier: Development Status :: 4 - Beta
Classifier: Intended Audience :: Developers
Classifier: Topic :: Scientific/Engineering :: Artificial Intelligence
Classifier: Programming Language :: Python :: 3.6
Classifier: Programming Language :: Python :: 3.7
Requires-Python: >=3.6
Requires-Dist: spacy (>=2.1.0)
Requires-Dist: stanfordnlp (<0.2.1,>=0.1.0)
